Metadata-Version: 2.1
Name: green-energy
Version: 0.1.0
Summary: A python library to access the Awattar Energy Price API.
Home-page: 
Author: 
Author-email: Ingmar Mueller <ingmar.mueller@kfw.de>, Mario Macai <mario.macai@accenture.com>, Melissa Schmidt <melissa.schmidt@accenture.com>, Georgia Moldovan <georgia.moldovan@accenture.com>, Felix Stark <felix.stark@kfw.de>
Project-URL: Bug Tracker, https://github.com/openkfw/smart_energy.green_energy_api/issues
Project-URL: Homepage, https://github.com/openkfw/smart_energy.green_energy_api
Keywords: green_energy,kfw,api,cloud
Classifier: Programming Language :: Python :: 3
Classifier: License :: OSI Approved :: GNU General Public License v3 (GPLv3)
Classifier: Operating System :: OS Independent
Provides: green_energy
Requires-Python: >=3.7
License-File: LICENSE
Requires-Dist: requests (>=2.27.1)
Provides-Extra: dev
Requires-Dist: black ; extra == 'dev'
Requires-Dist: pytest ; extra == 'dev'
Requires-Dist: python-dotenv ; extra == 'dev'
Requires-Dist: pre-commit ; extra == 'dev'
